parahash/__init__.py
parahash/__main__.py
parahash/cli.py
parahash/md5.py
parahash-0.1.0.dist-info/LICENSE
parahash-0.1.0.dist-info/METADATA
parahash-0.1.0.dist-info/WHEEL
parahash-0.1.0.dist-info/RECORD
