Metadata-Version: 2.1
Name: parahash
Version: 0.1.0
Summary: 
Home-page: https://github.com/VermiIIi0n/parahash
License: MIT
Keywords: utilities
Author: VermiIIi0n
Author-email: dungeon.behind0t@icloud.com
Requires-Python: >=3.12,<4.0
Classifier: Development Status :: 4 - Beta
Classifier: Framework :: Pytest
Classifier: Intended Audience :: Developers
Classifier: License :: OSI Approved :: MIT License
Classifier: Operating System :: OS Independent
Classifier: Programming Language :: Python :: 3
Classifier: Programming Language :: Python :: 3.12
Classifier: Programming Language :: Python :: Implementation :: CPython
Classifier: Programming Language :: Python :: Implementation :: PyPy
Classifier: Topic :: Utilities
Classifier: Typing :: Typed
Provides-Extra: all
Requires-Dist: bitarray (>=2.9.2,<3.0.0)
Requires-Dist: torch (>=2.3.0,<3.0.0) ; extra == "all"
Project-URL: Issues, https://github.com/VermiIIi0n/parahash/issues
